Metadata-Version: 1.0
Name: dsdaba-distributions
Version: 0.11
Summary: Gaussian and Binomial distributions
Home-page: UNKNOWN
Author: Yuchen Xie
Author-email: xie.yuc@husky.neu.edu
License: UNKNOWN
Platform: UNKNOWN
